bmi_package/__init__.py
bmi_package-0.0.2.dist-info/LICENSE
bmi_package-0.0.2.dist-info/METADATA
bmi_package-0.0.2.dist-info/WHEEL
bmi_package-0.0.2.dist-info/top_level.txt
bmi_package-0.0.2.dist-info/RECORD
