Metadata-Version: 2.1
Name: bmi-package
Version: 0.0.2
Summary: BMI Calculation package
Home-page: https://github.com/crypto597/code-20210109-saurabhkhare
Author: Saurabh Khare
Author-email: saurabhkhare597@gmail.com
License: MIT
Platform: UNKNOWN
Requires-Python: >=3.7
